pymultitaper/__init__.py
pymultitaper/spectral.py
pymultitaper-1.1.0.dist-info/licenses/LICENSE
pymultitaper-1.1.0.dist-info/METADATA
pymultitaper-1.1.0.dist-info/WHEEL
pymultitaper-1.1.0.dist-info/top_level.txt
pymultitaper-1.1.0.dist-info/RECORD
