Metadata-Version: 2.4
Name: pymultitaper
Version: 1.1.0
Summary: Fast easy-to-use multitaper spectrogram and spectrum calculation with Python
Author-email: Chao Kong <kongchao1998@gmail.com>
Project-URL: Documentation, https://fncokg.github.io/pymultitaper/
Project-URL: Repository, https://github.com/fncokg/pymultitaper/
Project-URL: Bug Tracker, https://github.com/fncokg/pymultitaper/issues
Classifier: Programming Language :: Python :: 3
Classifier: License :: OSI Approved :: MIT License
Classifier: Operating System :: OS Independent
Requires-Python: >=3.6
License-File: LICENSE
Requires-Dist: numpy
Requires-Dist: scipy
Requires-Dist: matplotlib
Dynamic: license-file
